{
  "userId": "user-03",
  "persona": {
    "age": 29,
    "profile": "Даваагаас эхэлнэ гэж боддог. Нэг удаа хазайвал өнөөдөр өнгөрлөө гэж мэдэрдэг. Маргаашаас илүү чанга барина."
  },
  "selectedAnswers": {
    "S1-W03": "Бараг бүх оролдлогоос хойш",
    "S1-W04": [
      "Калори тоолох",
      "Мацаг",
      "Орой хоол идэхгүй"
    ],
    "S1-W06": "Өнөөдөр өнгөрлөө, маргаашаас",
    "S1-F02": "Одоо бүх юм дууссан",
    "S1-X03": "Маш хүчтэй",
    "S1-S04": "Үгүй"
  },
  "freeTextAnswers": {
    "S1-V03": "Эхэндээ маш хатуу барьдаг. Нэг өдөр хазайхаар бүх юм дууссан юм шиг санагдаад маргаашаас бүр чанга барина гэж боддог."
  },
  "menstrualCycleAnswersIfAny": {},
  "generatedMode": "deep",
  "safetyMode": "deep",
  "primaryMechanism": "Control-Collapse Cycle",
  "secondaryMechanisms": [
    "Hunger-Safety / Scarcity Protection",
    "Perfectionism / All-or-Nothing Pattern"
  ],
  "simpleResult": {
    "stuckMoment": "Нэг удаа төлөвлөгөө зөрөхөд “өнөөдөр өнгөрлөө” гэж мэдрэгддэг.",
    "meaningBullets": [
      "Асуудал ганц удаа хазайсандаа биш.",
      "Тэр мөчөөс хойш дараагийн хоолноос хэвийн үргэлжлэх зам бүдгэрч байна.",
      "Маргаашаас илүү чанга барина гэсэн бодол тойргийг дахин эхлүүлж магадгүй."
    ],
    "firstStep": "Нэг хазайлтын дараа хэрэглэх “дараагийн хоолноос хэвийн үргэлжлүүлэх” дүрэмтэй бол.",
    "avoidForNow": "Нэг алдааны дараа бүхнийг дахин эхлүүлэх хатуу дэглэмээс түр зайлсхий.",
    "menstrualCycleNoteIfAny": ""
  },
  "detailedReportText": "Доорх нь дэлгэрэнгүй тайлбар. Эхний хэсгийг ойлгосон бол бүгдийг нь унших албагүй.\nГол зураг\nАсуудал нэг удаа хазайсандаа биш.\nТэр мөчөөс хойш “одоо нэгэнт өнгөрсөн” гэж бодогддог.\nТэгэхээр дараагийн хоолноос хэвийн үргэлжлэхэд хэцүү болдог.\nТэр үед хоол танд юу өгч байсан байж болох вэ?\nТэр үед хоол зүгээр нэг хоол биш байсан байж болно. Хоол танд түр амсхийх, тэнхээ орох, эсвэл өөртөө нэг юм өгсөн мэдрэмж өгч байсан байж магадгүй.\n- “Нэгэнт алдсан” гэсэн дарамтаас түр холдох\n- Хэт чанга дүрмийн эсрэг түр сулрах\n- Өөрийгөө буруутгах мэдрэмжээс хэсэг зай авах\nДавтагддаг тойрог\nШинэ төлөвлөгөө хэт чанга эхэлнэ ↓\nБага зэрэг хазайх мөч гарна ↓\n“Өнөөдөр өнгөрлөө” гэж бодогдоно ↓\nДараагийн хоолноос хэвийн үргэлжлэх зам бүдгэрнэ ↓\nИлүү их идэх эсвэл бүхлээр нь орхих хандлага гарна ↓\nДараа нь гэмшил нэмэгдэнэ ↓\nМаргаашаас илүү чанга барина гэж бодно\nҮүнийг юунаас харсан бэ?\nЭнэ тайлбар таны өгсөн мэдээлэл, бичсэн богино тайлбар дээр тулгуурласан. 7 хоногийн тэмдэглэл хийвэл аль өдөр, ямар үед илүү хүчтэй болдгийг илүү сайн ялгана.\nАсуудал яг юу биш вэ?\nАсуудал нэг удаа төлөвлөгөө алдсандаа биш. Гол нь буцаад хэвийн үргэлжлэх жижиг зам харагдахгүй болдог.\nОдоогоор болгоомжлох зүйлс\n- Төгс төлөвлөгөө\n- Нэг алдаа гарвал бүхнийг дахин эхлүүлэх сорил\n- Ичгүүрээр шахдаг хяналт\n- Алдаагаа нөхөх гэж маргааш нь илүү чангаруулах\nЭхний жижиг өөрчлөлт\nЭхний жижиг өөрчлөлт бол төгс төлөвлөгөө биш. Нэг хазайлтын дараа хэрэглэх “дараагийн хоолноос хэвийн үргэлжлүүлэх” дүрэмтэй болох.\n14 хоногийн туршилт\nЭхний 3 өдөр: “70% хангалттай” гэсэн нэг өгүүлбэр бичээд өдөр бүр харагдах газар тавь.\n4–10 дахь өдөр: төлөвлөгөө зөрсөн мөч гарвал дараагийн хоолыг шийтгэлгүй хэвийн хоол болго. Нөхөх гэж мацаг барихгүй.\n11–14 дахь өдөр: “өнөөдөр өнгөрлөө” бодол хэдэн удаа гарсан, хэдэн удаа дараагийн хоолноос үргэлжлүүлж чадсанаа тэмдэглэ.\nХэрвээ нэг өдөр алгасвал: маргааш илүү чанга барихгүй. Зүгээр дараагийн хоолноос эхэл.\n7 хоногоор нарийвчлах\nХэрвээ үүнийг илүү бодит өдөр тутмын түвшинд ялгахыг хүсвэл 7 хоногийн богино тэмдэглэлээр дараах хэсгүүдийг тодруулж болно.\n- Хэвийн үргэлжлүүлэхэд хэцүү мөч ямар өдөр илүү хүчтэй болдгийг тэмдэглэлээр ялгана.\n- Хоолны зай уртсах үе ямар өдөр илүү хүчтэй болдгийг тэмдэглэлээр ялгана.\n- Идэх хүсэл гарахын өмнөх 30 минут, оройн тэнхээ, хоол харагдах зэрэг ойрын нөхцөлийг тэмдэглэнэ.\n7 хоногоор нарийвчлах\nДотоод туршилтын хувилбар — энэ шатанд бодит төлбөр авахгүй.\nТуршилтын санал асуулга\nТа тайлангаа уншаад доорх асуултад үнэнээр нь хариулаарай. Бид энэ мэдээллийг тестийн ойлгомж, найруулга, хэрэгцээг сайжруулахад ашиглана.\nТест бөглөх явцад эвгүй, ичмээр, шүүсэн мэдрэмж төрсөн үү?\nҮгүй\nБага зэрэг\nТийм\nАль хэсэг дээр?\nАсуултууд ойлгомжтой байсан уу?\nМаш ойлгомжтой\nЕрөнхийдөө ойлгомжтой\nЗарим нь ойлгомжгүй\nИхэнх нь ойлгомжгүй\nОйлгомжгүй санагдсан асуулт байвал бичнэ үү.\nТайлан таны нөхцөлтэй хэр нийцсэн бэ?\n1 = огт нийцээгүй, 10 = маш сайн нийцсэн\nТайлангийн эхний “Товч хариу” хэсэг ойлгомжтой байсан уу?\nТийм, шууд ойлгосон\nЕрөнхийдөө ойлгосон\nДахин уншиж байж ойлгосон\nОйлгоогүй\nОйлгомжгүй байсан хэсгийг бичнэ үү.\nТайлан уншихад “намайг ойлгож байна” гэсэн мэдрэмж төрсөн үү?\nТийм\nЗарим хэсэг дээр\nҮгүй\nЯагаад?\nТайлангаас танд хэрэгтэй шинэ өнцөг, шинэ ойлголт гарсан уу?\nТийм\nБага зэрэг\nҮгүй\nЯмар хэсэг?\nТайлан хэт ерөнхий, AI шиг, эсвэл худлаа санагдсан хэсэг байсан уу?\nҮгүй\nТийм\nАль хэсэг?\nТайлангийн хэл найруулга ямар санагдсан бэ?\nБайгалийн монгол хэлтэй\nЗарим хэсэг хиймэл\nХэт албархуу\nХэт зөөлөн/бөөрөнхий\nЗасах санал:\nЭнэ тайланг 29,000 төгрөгөөр авахад үнэ цэнтэй санагдах уу?\nТийм\nМагадгүй\nҮгүй\nЯагаад?\nХамгийн хэрэгтэй санагдсан хэсэг юу байсан бэ?\nХамгийн засмаар санагдсан хэсэг юу байсан бэ?\nСанал илгээх\nСаналын экспорт\nСонголт руу буцах Шинээр эхлэх",
  "fullReportText": "Гүн зураглалын тайлан\nТаны гүн зураглал бэлэн боллоо\nДоорх нь таны өгсөн мэдээллээс гарсан эхний тайлбар. Өөрийгөө буруутгах гэж биш, өдөрт яг хаана хэцүү болдгийг тайван харах гэж уншаарай.\nТовч хариу\n1. Таны гол гацдаг мөч\nНэг удаа төлөвлөгөө зөрөхөд “өнөөдөр өнгөрлөө” гэж мэдрэгддэг.\n2. Энэ юу гэсэн үг вэ?\n- Асуудал ганц удаа хазайсандаа биш.\n- Тэр мөчөөс хойш дараагийн хоолноос хэвийн үргэлжлэх зам бүдгэрч байна.\n- Маргаашаас илүү чанга барина гэсэн бодол тойргийг дахин эхлүүлж магадгүй.\n3. Эхлээд хийх нэг жижиг зүйл\nНэг хазайлтын дараа хэрэглэх “дараагийн хоолноос хэвийн үргэлжлүүлэх” дүрэмтэй бол.\n4. Одоогоор түр болгоомжлох зүйл\nНэг алдааны дараа бүхнийг дахин эхлүүлэх хатуу дэглэмээс түр зайлсхий.\nДэлгэрэнгүй тайлан\nДоорх нь дэлгэрэнгүй тайлбар. Эхний хэсгийг ойлгосон бол бүгдийг нь унших албагүй.\nГол зураг\nАсуудал нэг удаа хазайсандаа биш.\nТэр мөчөөс хойш “одоо нэгэнт өнгөрсөн” гэж бодогддог.\nТэгэхээр дараагийн хоолноос хэвийн үргэлжлэхэд хэцүү болдог.\nТэр үед хоол танд юу өгч байсан байж болох вэ?\nТэр үед хоол зүгээр нэг хоол биш байсан байж болно. Хоол танд түр амсхийх, тэнхээ орох, эсвэл өөртөө нэг юм өгсөн мэдрэмж өгч байсан байж магадгүй.\n- “Нэгэнт алдсан” гэсэн дарамтаас түр холдох\n- Хэт чанга дүрмийн эсрэг түр сулрах\n- Өөрийгөө буруутгах мэдрэмжээс хэсэг зай авах\nДавтагддаг тойрог\nШинэ төлөвлөгөө хэт чанга эхэлнэ ↓\nБага зэрэг хазайх мөч гарна ↓\n“Өнөөдөр өнгөрлөө” гэж бодогдоно ↓\nДараагийн хоолноос хэвийн үргэлжлэх зам бүдгэрнэ ↓\nИлүү их идэх эсвэл бүхлээр нь орхих хандлага гарна ↓\nДараа нь гэмшил нэмэгдэнэ ↓\nМаргаашаас илүү чанга барина гэж бодно\nҮүнийг юунаас харсан бэ?\nЭнэ тайлбар таны өгсөн мэдээлэл, бичсэн богино тайлбар дээр тулгуурласан. 7 хоногийн тэмдэглэл хийвэл аль өдөр, ямар үед илүү хүчтэй болдгийг илүү сайн ялгана.\nАсуудал яг юу биш вэ?\nАсуудал нэг удаа төлөвлөгөө алдсандаа биш. Гол нь буцаад хэвийн үргэлжлэх жижиг зам харагдахгүй болдог.\nОдоогоор болгоомжлох зүйлс\n- Төгс төлөвлөгөө\n- Нэг алдаа гарвал бүхнийг дахин эхлүүлэх сорил\n- Ичгүүрээр шахдаг хяналт\n- Алдаагаа нөхөх гэж маргааш нь илүү чангаруулах\nЭхний жижиг өөрчлөлт\nЭхний жижиг өөрчлөлт бол төгс төлөвлөгөө биш. Нэг хазайлтын дараа хэрэглэх “дараагийн хоолноос хэвийн үргэлжлүүлэх” дүрэмтэй болох.\n14 хоногийн туршилт\nЭхний 3 өдөр: “70% хангалттай” гэсэн нэг өгүүлбэр бичээд өдөр бүр харагдах газар тавь.\n4–10 дахь өдөр: төлөвлөгөө зөрсөн мөч гарвал дараагийн хоолыг шийтгэлгүй хэвийн хоол болго. Нөхөх гэж мацаг барихгүй.\n11–14 дахь өдөр: “өнөөдөр өнгөрлөө” бодол хэдэн удаа гарсан, хэдэн удаа дараагийн хоолноос үргэлжлүүлж чадсанаа тэмдэглэ.\nХэрвээ нэг өдөр алгасвал: маргааш илүү чанга барихгүй. Зүгээр дараагийн хоолноос эхэл.\n7 хоногоор нарийвчлах\nХэрвээ үүнийг илүү бодит өдөр тутмын түвшинд ялгахыг хүсвэл 7 хоногийн богино тэмдэглэлээр дараах хэсгүүдийг тодруулж болно.\n- Хэвийн үргэлжлүүлэхэд хэцүү мөч ямар өдөр илүү хүчтэй болдгийг тэмдэглэлээр ялгана.\n- Хоолны зай уртсах үе ямар өдөр илүү хүчтэй болдгийг тэмдэглэлээр ялгана.\n- Идэх хүсэл гарахын өмнөх 30 минут, оройн тэнхээ, хоол харагдах зэрэг ойрын нөхцөлийг тэмдэглэнэ.\n7 хоногоор нарийвчлах\nДотоод туршилтын хувилбар — энэ шатанд бодит төлбөр авахгүй.\nТуршилтын санал асуулга\nТа тайлангаа уншаад доорх асуултад үнэнээр нь хариулаарай. Бид энэ мэдээллийг тестийн ойлгомж, найруулга, хэрэгцээг сайжруулахад ашиглана.\nТест бөглөх явцад эвгүй, ичмээр, шүүсэн мэдрэмж төрсөн үү?\nҮгүй\nБага зэрэг\nТийм\nАль хэсэг дээр?\nАсуултууд ойлгомжтой байсан уу?\nМаш ойлгомжтой\nЕрөнхийдөө ойлгомжтой\nЗарим нь ойлгомжгүй\nИхэнх нь ойлгомжгүй\nОйлгомжгүй санагдсан асуулт байвал бичнэ үү.\nТайлан таны нөхцөлтэй хэр нийцсэн бэ?\n1 = огт нийцээгүй, 10 = маш сайн нийцсэн\nТайлангийн эхний “Товч хариу” хэсэг ойлгомжтой байсан уу?\nТийм, шууд ойлгосон\nЕрөнхийдөө ойлгосон\nДахин уншиж байж ойлгосон\nОйлгоогүй\nОйлгомжгүй байсан хэсгийг бичнэ үү.\nТайлан уншихад “намайг ойлгож байна” гэсэн мэдрэмж төрсөн үү?\nТийм\nЗарим хэсэг дээр\nҮгүй\nЯагаад?\nТайлангаас танд хэрэгтэй шинэ өнцөг, шинэ ойлголт гарсан уу?\nТийм\nБага зэрэг\nҮгүй\nЯмар хэсэг?\nТайлан хэт ерөнхий, AI шиг, эсвэл худлаа санагдсан хэсэг байсан уу?\nҮгүй\nТийм\nАль хэсэг?\nТайлангийн хэл найруулга ямар санагдсан бэ?\nБайгалийн монгол хэлтэй\nЗарим хэсэг хиймэл\nХэт албархуу\nХэт зөөлөн/бөөрөнхий\nЗасах санал:\nЭнэ тайланг 29,000 төгрөгөөр авахад үнэ цэнтэй санагдах уу?\nТийм\nМагадгүй\nҮгүй\nЯагаад?\nХамгийн хэрэгтэй санагдсан хэсэг юу байсан бэ?\nХамгийн засмаар санагдсан хэсэг юу байсан бэ?\nСанал илгээх\nСаналын экспорт\nСонголт руу буцах Шинээр эхлэх",
  "feedbackSimulation": {
    "simpleResultClarity": "Тийм, шууд ойлгосон",
    "simpleResultClarityDetail": "Эхний товч хэсгээс гол санаа ойлгогдож байна.",
    "reportFitRating": 9,
    "feltUnderstood": "Тийм",
    "feltUnderstoodReason": "Миний нөхцөлтэй ойр тайлбарласан.",
    "newInsight": "Тийм",
    "aiGenericFeeling": "Үгүй",
    "aiGenericDetail": "",
    "valueAt9900": "Тийм",
    "valueReason": "Товч хариу болон эхний алхам хэрэгтэй санагдана.",
    "mostUsefulPart": "Нэг удаа төлөвлөгөө зөрөхөд “өнөөдөр өнгөрлөө” гэж мэдрэгддэг.",
    "mostNeedsFix": "Одоогоор ноцтой засвар алга."
  },
  "audit": {
    "routeCorrect": true,
    "simpleAnswerUnderstandable": true,
    "reportMatchesPersona": true,
    "noShame": true,
    "noBannedTerms": true,
    "firstStepPractical": true,
    "safetyCorrect": true,
    "verdict": "PASS"
  },
  "scores": {
    "simpleAnswerClarity": 9,
    "personaFit": 9,
    "humanMongolian": 8,
    "lowAiSmell": 8,
    "emotionalSafety": 9,
    "actionability": 9,
    "paidValue": 8
  },
  "issuesFound": [],
  "bannedTermsFound": []
}
